{
    "1": {
        "0": { "strongs": "935", "eng": "And came" },
        "1": { "strongs": "376", "eng": "the men" },
        "2": { "strongs": "7157", "eng": "Kirjath Jearim" },
        "3": { "strongs": "5927", "eng": "and took" },
        "4": { "strongs": "853", "eng": "-" },
        "5": { "strongs": "727", "eng": "the ark" },
        "6": { "strongs": "3068", "eng": "of Yahweh" },
        "7": { "strongs": "935", "eng": "and brought" },
        "8": { "strongs": "853", "eng": "it" },
        "9": { "strongs": "413", "eng": "into" },
        "10": { "strongs": "1004", "eng": "the house" },
        "11": { "strongs": "41", "eng": "of Abinadab" },
        "12": { "strongs": "1389", "eng": "on the hill" },
        "13": { "strongs": "853", "eng": "and" },
        "14": { "strongs": "499", "eng": "Eleazar" },
        "15": { "strongs": "1121", "eng": "his son" },
        "16": { "strongs": "6942", "eng": "consecrated" },
        "17": { "strongs": "8104", "eng": "to keep" },
        "18": { "strongs": "853", "eng": "-" },
        "19": { "strongs": "727", "eng": "the ark" },
        "20": { "strongs": "3068", "eng": "of Yahweh"
        }
    },
    "2": {
        "0": { "strongs": "1961", "eng": "So it was" },
        "1": { "strongs": "3117", "eng": "that" },
        "2": { "strongs": "3427", "eng": "remained" },
        "3": { "strongs": "727", "eng": "the ark" },
        "4": { "strongs": "7157", "eng": "Kirjath Jearim" },
        "5": { "strongs": "7235", "eng": "and long" },
        "6": { "strongs": "3117", "eng": "a time" },
        "7": { "strongs": "1961", "eng": "and it was [there]" },
        "8": { "strongs": "6242", "eng": "twenty" },
        "9": { "strongs": "8141", "eng": "years" },
        "10": { "strongs": "5091", "eng": "and lamented" },
        "11": { "strongs": "3605", "eng": "all" },
        "12": { "strongs": "1004", "eng": "the house" },
        "13": { "strongs": "3478", "eng": "of Israel" },
        "14": { "strongs": "310", "eng": "after" },
        "15": { "strongs": "3068", "eng": "Yahweh"
        }
    },
    "3": {
        "0": { "strongs": "559", "eng": "And spoke" },
        "1": { "strongs": "8050", "eng": "Samuel" },
        "2": { "strongs": "413", "eng": "to" },
        "3": { "strongs": "3605", "eng": "all" },
        "4": { "strongs": "1004", "eng": "the house" },
        "5": { "strongs": "3478", "eng": "of Israel" },
        "6": { "strongs": "559", "eng": "saying" },
        "7": { "strongs": "518", "eng": "if" },
        "8": { "strongs": "3605", "eng": "with all" },
        "9": { "strongs": "3824", "eng": "your heart" },
        "10": { "strongs": "859", "eng": "you" },
        "11": { "strongs": "7725", "eng": "return" },
        "12": { "strongs": "413", "eng": "to" },
        "13": { "strongs": "3068", "eng": "Yahweh" },
        "14": { "strongs": "5493", "eng": "[then] put away" },
        "15": { "strongs": "853", "eng": "-" },
        "16": { "strongs": "430", "eng": "gods" },
        "17": { "strongs": "5236", "eng": "the foreign" },
        "18": { "strongs": "8432", "eng": "from among you" },
        "19": { "strongs": "6252", "eng": "and the Ashtoreths" },
        "20": { "strongs": "3559", "eng": "and prepare" },
        "21": { "strongs": "3824", "eng": "your hearts" },
        "22": { "strongs": "413", "eng": "for" },
        "23": { "strongs": "3068", "eng": "Yahweh" },
        "24": { "strongs": "5647", "eng": "and serve Him" },
        "25": { "strongs": "905", "eng": "only" },
        "26": { "strongs": "5337", "eng": "and He will deliver" },
        "27": { "strongs": "853", "eng": "you" },
        "28": { "strongs": "3027", "eng": "from the hand" },
        "29": { "strongs": "6430", "eng": "of the Philistines"
        }
    },
    "4": {
        "0": { "strongs": "5493", "eng": "So put away" },
        "1": { "strongs": "1121", "eng": "the sons" },
        "2": { "strongs": "3478", "eng": "of Israel" },
        "3": { "strongs": "853", "eng": "-" },
        "4": { "strongs": "1168", "eng": "the Baals" },
        "5": { "strongs": "853", "eng": "and" },
        "6": { "strongs": "6252", "eng": "the Ashtoreths" },
        "7": { "strongs": "5647", "eng": "and served" },
        "8": { "strongs": "853", "eng": "-" },
        "9": { "strongs": "3068", "eng": "Yahweh" },
        "10": { "strongs": "905", "eng": "only"
        }
    },
    "5": {
        "0": { "strongs": "559", "eng": "And said" },
        "1": { "strongs": "8050", "eng": "Samuel" },
        "2": { "strongs": "6908", "eng": "Gather" },
        "3": { "strongs": "853", "eng": "-" },
        "4": { "strongs": "3605", "eng": "all" },
        "5": { "strongs": "3478", "eng": "Israel" },
        "6": { "strongs": "4709", "eng": "to Mizpah" },
        "7": { "strongs": "6419", "eng": "and I will pray" },
        "8": { "strongs": "1157", "eng": "for you" },
        "9": { "strongs": "413", "eng": "to" },
        "10": { "strongs": "3068", "eng": "Yahweh"
        }
    },
    "6": {
        "0": { "strongs": "6908", "eng": "So they gathered together" },
        "1": { "strongs": "4709", "eng": "at Mizpah" },
        "2": { "strongs": "7579", "eng": "and drew" },
        "3": { "strongs": "4325", "eng": "water" },
        "4": { "strongs": "8210", "eng": "and poured [it] out" },
        "5": { "strongs": "6440", "eng": "before" },
        "6": { "strongs": "3068", "eng": "Yahweh" },
        "7": { "strongs": "6684", "eng": "and they fasted" },
        "8": { "strongs": "3117", "eng": "day" },
        "9": { "strongs": "1931", "eng": "that" },
        "10": { "strongs": "559", "eng": "and said" },
        "11": { "strongs": "8033", "eng": "there" },
        "12": { "strongs": "2398", "eng": "we have sinned" },
        "13": { "strongs": "3068", "eng": "against Yahweh" },
        "14": { "strongs": "8199", "eng": "And judged" },
        "15": { "strongs": "8050", "eng": "Samuel" },
        "16": { "strongs": "853", "eng": "-" },
        "17": { "strongs": "1121", "eng": "the sons" },
        "18": { "strongs": "3478", "eng": "of Israel" },
        "19": { "strongs": "4709", "eng": "at Mizpah"
        }
    },
    "7": {
        "0": { "strongs": "8085", "eng": "And when heard" },
        "1": { "strongs": "6430", "eng": "the Philistines" },
        "2": { "strongs": "3588", "eng": "that" },
        "3": { "strongs": "6908", "eng": "had gathered together" },
        "4": { "strongs": "1121", "eng": "the sons" },
        "5": { "strongs": "3478", "eng": "of Israel" },
        "6": { "strongs": "4709", "eng": "at Mizpah" },
        "7": { "strongs": "5927", "eng": "and went up" },
        "8": { "strongs": "5633", "eng": "the lords" },
        "9": { "strongs": "6430", "eng": "of the Philistines" },
        "10": { "strongs": "413", "eng": "against" },
        "11": { "strongs": "3478", "eng": "Israel" },
        "12": { "strongs": "8085", "eng": "And when heard [of it]" },
        "13": { "strongs": "1121", "eng": "the sons" },
        "14": { "strongs": "3478", "eng": "of Israel" },
        "15": { "strongs": "3372", "eng": "and they were afraid" },
        "16": { "strongs": "6440", "eng": "of" },
        "17": { "strongs": "6430", "eng": "the Philistines"
        }
    },
    "8": {
        "0": { "strongs": "559", "eng": "So said" },
        "1": { "strongs": "1121", "eng": "the sons" },
        "2": { "strongs": "3478", "eng": "of Israel" },
        "3": { "strongs": "413", "eng": "to" },
        "4": { "strongs": "8050", "eng": "Samuel" },
        "5": { "strongs": "408", "eng": "not" },
        "6": { "strongs": "2790", "eng": "do cease" },
        "7": { "strongs": "4480", "eng": "for us" },
        "8": { "strongs": "2199", "eng": "to cry out" },
        "9": { "strongs": "413", "eng": "to" },
        "10": { "strongs": "3068", "eng": "Yahweh" },
        "11": { "strongs": "430", "eng": "our God" },
        "12": { "strongs": "3467", "eng": "that He may save us" },
        "13": { "strongs": "3027", "eng": "from the hand" },
        "14": { "strongs": "6430", "eng": "of the Philistines"
        }
    },
    "9": {
        "0": { "strongs": "3947", "eng": "And took" },
        "1": { "strongs": "8050", "eng": "Samuel" },
        "2": { "strongs": "2924", "eng": "lamb" },
        "3": { "strongs": "2461", "eng": "suckling" },
        "4": { "strongs": "259", "eng": "a" },
        "5": { "strongs": "5927", "eng": "and offered [it]" },
        "6": { "strongs": "5930", "eng": "[as] a burnt offering" },
        "7": { "strongs": "3632", "eng": "whole" },
        "8": { "strongs": "3068", "eng": "to Yahweh" },
        "9": { "strongs": "2199", "eng": "and cried out" },
        "10": { "strongs": "8050", "eng": "Samuel" },
        "11": { "strongs": "413", "eng": "to" },
        "12": { "strongs": "3068", "eng": "Yahweh" },
        "13": { "strongs": "1157", "eng": "for" },
        "14": { "strongs": "3478", "eng": "Israel" },
        "15": { "strongs": "6030", "eng": "and answered him" },
        "16": { "strongs": "3068", "eng": "Yahweh"
        }
    },
    "10": {
        "0": { "strongs": "1961", "eng": "And as was" },
        "1": { "strongs": "8050", "eng": "Samuel" },
        "2": { "strongs": "5927", "eng": "offering up" },
        "3": { "strongs": "5930", "eng": "the burnt offering" },
        "4": { "strongs": "6430", "eng": "and the Philistines" },
        "5": { "strongs": "5066", "eng": "drew near" },
        "6": { "strongs": "4421", "eng": "to battle" },
        "7": { "strongs": "3478", "eng": "against Israel" },
        "8": { "strongs": "7481", "eng": "But thundered" },
        "9": { "strongs": "3068", "eng": "Yahweh" },
        "10": { "strongs": "6963", "eng": "with a thunder" },
        "11": { "strongs": "1419", "eng": "loud" },
        "12": { "strongs": "3117", "eng": "day" },
        "13": { "strongs": "1931", "eng": "that" },
        "14": { "strongs": "5921", "eng": "upon" },
        "15": { "strongs": "6430", "eng": "the Philistines" },
        "16": { "strongs": "2000", "eng": "so confused them" },
        "17": { "strongs": "5062", "eng": "that they were overcome" },
        "18": { "strongs": "6440", "eng": "before" },
        "19": { "strongs": "3478", "eng": "Israel"
        }
    },
    "11": {
        "0": { "strongs": "3318", "eng": "And went out" },
        "1": { "strongs": "582", "eng": "the men" },
        "2": { "strongs": "3478", "eng": "of Israel" },
        "3": { "strongs": "4480", "eng": "from" },
        "4": { "strongs": "4709", "eng": "Mizpah" },
        "5": { "strongs": "7291", "eng": "and pursued" },
        "6": { "strongs": "853", "eng": "-" },
        "7": { "strongs": "6430", "eng": "the Philistines" },
        "8": { "strongs": "5221", "eng": "and drove them back" },
        "9": { "strongs": "5704", "eng": "until" },
        "10": { "strongs": "8478", "eng": "as far as" },
        "11": { "strongs": "1033", "eng": "Beth Car"
        }
    },
    "12": {
        "0": { "strongs": "3947", "eng": "And took" },
        "1": { "strongs": "8050", "eng": "Samuel" },
        "2": { "strongs": "68", "eng": "stone" },
        "3": { "strongs": "259", "eng": "a" },
        "4": { "strongs": "7760", "eng": "and set [it] up" },
        "5": { "strongs": "996", "eng": "between" },
        "6": { "strongs": "4709", "eng": "Mizpah" },
        "7": { "strongs": "996", "eng": "and" },
        "8": { "strongs": "8129", "eng": "Shen" },
        "9": { "strongs": "7121", "eng": "and called" },
        "10": { "strongs": "853", "eng": "-" },
        "11": { "strongs": "8034", "eng": "its name" },
        "12": { "strongs": "72", "eng": "Ebenezer" },
        "13": { "strongs": "559", "eng": "and saying" },
        "14": { "strongs": "5704", "eng": "thus far" },
        "15": { "strongs": "2008", "eng": "thus" },
        "16": { "strongs": "5826", "eng": "has helped us" },
        "17": { "strongs": "3068", "eng": "Yahweh"
        }
    },
    "13": {
        "0": { "strongs": "3665", "eng": "So were subdued" },
        "1": { "strongs": "6430", "eng": "the Philistines" },
        "2": { "strongs": "3808", "eng": "and not" },
        "3": { "strongs": "3254", "eng": "again" },
        "4": { "strongs": "5750", "eng": "anymore" },
        "5": { "strongs": "935", "eng": "they did come" },
        "6": { "strongs": "1366", "eng": "into the territory" },
        "7": { "strongs": "3478", "eng": "of Israel" },
        "8": { "strongs": "1961", "eng": "And was" },
        "9": { "strongs": "3027", "eng": "the hand" },
        "10": { "strongs": "3068", "eng": "of Yahweh" },
        "11": { "strongs": "6430", "eng": "against the Philistines" },
        "12": { "strongs": "3605", "eng": "all" },
        "13": { "strongs": "3117", "eng": "the days" },
        "14": { "strongs": "8050", "eng": "of Samuel"
        }
    },
    "14": {
        "0": { "strongs": "7725", "eng": "And were restored" },
        "1": { "strongs": "5892", "eng": "the cities" },
        "2": { "strongs": "834", "eng": "which" },
        "3": { "strongs": "3947", "eng": "had taken" },
        "4": { "strongs": "6430", "eng": "the Philistines" },
        "5": { "strongs": "853", "eng": "from" },
        "6": { "strongs": "3478", "eng": "Israel" },
        "7": { "strongs": "3478", "eng": "to Israel" },
        "8": { "strongs": "6138", "eng": "from Ekron" },
        "9": { "strongs": "5704", "eng": "and to" },
        "10": { "strongs": "1661", "eng": "Gath" },
        "11": { "strongs": "853", "eng": "and" },
        "12": { "strongs": "1366", "eng": "its territory" },
        "13": { "strongs": "5337", "eng": "recovered" },
        "14": { "strongs": "3478", "eng": "Israel" },
        "15": { "strongs": "3027", "eng": "from the hand" },
        "16": { "strongs": "6430", "eng": "of the Philistines" },
        "17": { "strongs": "1961", "eng": "And there was" },
        "18": { "strongs": "7965", "eng": "peace" },
        "19": { "strongs": "996", "eng": "between" },
        "20": { "strongs": "3478", "eng": "Israel" },
        "21": { "strongs": "996", "eng": "and" },
        "22": { "strongs": "567", "eng": "the Amorites"
        }
    },
    "15": {
        "0": { "strongs": "8199", "eng": "And judged" },
        "1": { "strongs": "8050", "eng": "Samuel" },
        "2": { "strongs": "853", "eng": "-" },
        "3": { "strongs": "3478", "eng": "Israel" },
        "4": { "strongs": "3605", "eng": "all" },
        "5": { "strongs": "3117", "eng": "the days" },
        "6": { "strongs": "2416", "eng": "of his life"
        }
    },
    "16": {
        "0": { "strongs": "1980", "eng": "And He went" },
        "1": { "strongs": "1767", "eng": "from" },
        "2": { "strongs": "8141", "eng": "year" },
        "3": { "strongs": "8141", "eng": "to year" },
        "4": { "strongs": "5437", "eng": "and on a circuit" },
        "5": { "strongs": "1008", "eng": "Bethel" },
        "6": { "strongs": "1537", "eng": "and Gilgal" },
        "7": { "strongs": "4709", "eng": "and Mizpah" },
        "8": { "strongs": "8199", "eng": "and judged" },
        "9": { "strongs": "853", "eng": "-" },
        "10": { "strongs": "3478", "eng": "Israel" },
        "11": { "strongs": "853", "eng": "in" },
        "12": { "strongs": "3605", "eng": "all" },
        "13": { "strongs": "4725", "eng": "places" },
        "14": { "strongs": "428", "eng": "these"
        }
    },
    "17": {
        "0": { "strongs": "8666", "eng": "But he always returned" },
        "1": { "strongs": "7414", "eng": "to Ramah" },
        "2": { "strongs": "3588", "eng": "for" },
        "3": { "strongs": "8033", "eng": "[was] there" },
        "4": { "strongs": "1004", "eng": "his home" },
        "5": { "strongs": "8033", "eng": "and there" },
        "6": { "strongs": "8199", "eng": "he judged" },
        "7": { "strongs": "853", "eng": "-" },
        "8": { "strongs": "3478", "eng": "Israel" },
        "9": { "strongs": "1129", "eng": "and he built" },
        "10": { "strongs": "8033", "eng": "there" },
        "11": { "strongs": "4196", "eng": "an altar" },
        "12": { "strongs": "3068", "eng": "to Yahweh"
        }
    }
}