{
    "1": {
        "0": { "strongs": "6680", "eng": "Then commanded" },
        "1": { "strongs": "4872", "eng": "Moses" },
        "2": { "strongs": "2205", "eng": "and with the elders" },
        "3": { "strongs": "3478", "eng": "of Israel" },
        "4": { "strongs": "853", "eng": "-" },
        "5": { "strongs": "5971", "eng": "the people" },
        "6": { "strongs": "559", "eng": "saying" },
        "7": { "strongs": "8104", "eng": "Keep" },
        "8": { "strongs": "853", "eng": "-" },
        "9": { "strongs": "3605", "eng": "all" },
        "10": { "strongs": "4687", "eng": "the commandments" },
        "11": { "strongs": "834", "eng": "which" },
        "12": { "strongs": "595", "eng": "I" },
        "13": { "strongs": "6680", "eng": "command" },
        "14": { "strongs": "853", "eng": "you" },
        "15": { "strongs": "3117", "eng": "today"
        }
    },
    "2": {
        "0": { "strongs": "1961", "eng": "And it shall be" },
        "1": { "strongs": "3117", "eng": "on the day" },
        "2": { "strongs": "834", "eng": "when" },
        "3": { "strongs": "5674", "eng": "you cross over" },
        "4": { "strongs": "853", "eng": "-" },
        "5": { "strongs": "3383", "eng": "the Jordan" },
        "6": { "strongs": "413", "eng": "to" },
        "7": { "strongs": "776", "eng": "the land" },
        "8": { "strongs": "834", "eng": "which" },
        "9": { "strongs": "3068", "eng": "Yahweh" },
        "10": { "strongs": "430", "eng": "your God" },
        "11": { "strongs": "5414", "eng": "is giving" },
        "12": { "strongs": "6965", "eng": "that you shall set up" },
        "13": { "strongs": "68", "eng": "stones" },
        "14": { "strongs": "1419", "eng": "large" },
        "15": { "strongs": "7874", "eng": "and whitewash" },
        "16": { "strongs": "853", "eng": "them" },
        "17": { "strongs": "7874", "eng": "with lime"
        }
    },
    "3": {
        "0": { "strongs": "3789", "eng": "And You shall write" },
        "1": { "strongs": "5921", "eng": "on them" },
        "2": { "strongs": "853", "eng": "-" },
        "3": { "strongs": "3605", "eng": "all" },
        "4": { "strongs": "1697", "eng": "the words" },
        "5": { "strongs": "8451", "eng": "of law" },
        "6": { "strongs": "2063", "eng": "this" },
        "7": { "strongs": "5674", "eng": "when you have crossed over" },
        "8": { "strongs": "4616", "eng": "to the end that" },
        "9": { "strongs": "834", "eng": "-" },
        "10": { "strongs": "935", "eng": "you may enter" },
        "11": { "strongs": "413", "eng": "into" },
        "12": { "strongs": "776", "eng": "the land" },
        "13": { "strongs": "834", "eng": "which" },
        "14": { "strongs": "3068", "eng": "Yahweh" },
        "15": { "strongs": "430", "eng": "your God" },
        "16": { "strongs": "5414", "eng": "is giving" },
        "17": { "strongs": "776", "eng": "a land" },
        "18": { "strongs": "2100", "eng": "flowing" },
        "19": { "strongs": "2461", "eng": "with milk" },
        "20": { "strongs": "1706", "eng": "and honey" },
        "21": { "strongs": "834", "eng": "just as" },
        "22": { "strongs": "1696", "eng": "promised" },
        "23": { "strongs": "3068", "eng": "Yahweh" },
        "24": { "strongs": "430", "eng": "God" },
        "25": { "strongs": "1", "eng": "of your fathers"
        }
    },
    "4": {
        "0": { "strongs": "1961", "eng": "Therefore it shall be" },
        "1": { "strongs": "5674", "eng": "when you have crossed over" },
        "2": { "strongs": "853", "eng": "-" },
        "3": { "strongs": "3383", "eng": "the Jordan" },
        "4": { "strongs": "6965", "eng": "[that] you shall set up" },
        "5": { "strongs": "853", "eng": "-" },
        "6": { "strongs": "68", "eng": "stones" },
        "7": { "strongs": "428", "eng": "these" },
        "8": { "strongs": "834", "eng": "which" },
        "9": { "strongs": "595", "eng": "I" },
        "10": { "strongs": "6680", "eng": "command" },
        "11": { "strongs": "853", "eng": "you" },
        "12": { "strongs": "3117", "eng": "today" },
        "13": { "strongs": "2022", "eng": "on Mount" },
        "14": { "strongs": "5858", "eng": "Ebal" },
        "15": { "strongs": "7874", "eng": "and you shall whitewash" },
        "16": { "strongs": "853", "eng": "them" },
        "17": { "strongs": "7874", "eng": "with lime"
        }
    },
    "5": {
        "0": { "strongs": "1129", "eng": "Moreover, you shall build" },
        "1": { "strongs": "8033", "eng": "there" },
        "2": { "strongs": "4196", "eng": "an altar" },
        "3": { "strongs": "3068", "eng": "to Yahweh" },
        "4": { "strongs": "430", "eng": "your God" },
        "5": { "strongs": "4196", "eng": "an altar" },
        "6": { "strongs": "68", "eng": "of stones" },
        "7": { "strongs": "3808", "eng": "not" },
        "8": { "strongs": "5130", "eng": "you shall use" },
        "9": { "strongs": "5921", "eng": "on them" },
        "10": { "strongs": "1270", "eng": "an iron [tool]"
        }
    },
    "6": {
        "0": { "strongs": "68", "eng": "With stones" },
        "1": { "strongs": "8003", "eng": "whole" },
        "2": { "strongs": "1129", "eng": "You shall build" },
        "3": { "strongs": "853", "eng": "-" },
        "4": { "strongs": "4196", "eng": "the altar" },
        "5": { "strongs": "3068", "eng": "of Yahweh" },
        "6": { "strongs": "430", "eng": "your God" },
        "7": { "strongs": "5927", "eng": "and offer" },
        "8": { "strongs": "5921", "eng": "on it" },
        "9": { "strongs": "5930", "eng": "burnt offerings" },
        "10": { "strongs": "3068", "eng": "to Yahweh" },
        "11": { "strongs": "430", "eng": "your God"
        }
    },
    "7": {
        "0": { "strongs": "2076", "eng": "and you shall sacrifice" },
        "1": { "strongs": "8002", "eng": "peace offerings" },
        "2": { "strongs": "398", "eng": "and shall eat" },
        "3": { "strongs": "8033", "eng": "there" },
        "4": { "strongs": "8055", "eng": "and rejoice" },
        "5": { "strongs": "6440", "eng": "before" },
        "6": { "strongs": "3068", "eng": "Yahweh" },
        "7": { "strongs": "430", "eng": "your God"
        }
    },
    "8": {
        "0": { "strongs": "3789", "eng": "And you shall write" },
        "1": { "strongs": "5921", "eng": "on" },
        "2": { "strongs": "68", "eng": "the stones" },
        "3": { "strongs": "853", "eng": "-" },
        "4": { "strongs": "3605", "eng": "all" },
        "5": { "strongs": "1697", "eng": "the words" },
        "6": { "strongs": "8451", "eng": "of law" },
        "7": { "strongs": "2063", "eng": "this" },
        "8": { "strongs": "874", "eng": "plainly" },
        "9": { "strongs": "3190", "eng": "very"
        }
    },
    "9": {
        "0": { "strongs": "1696", "eng": "And spoke" },
        "1": { "strongs": "4872", "eng": "Moses" },
        "2": { "strongs": "3548", "eng": "and the priests" },
        "3": { "strongs": "3881", "eng": "the Levites" },
        "4": { "strongs": "413", "eng": "to" },
        "5": { "strongs": "3605", "eng": "all" },
        "6": { "strongs": "3478", "eng": "Israel" },
        "7": { "strongs": "559", "eng": "saying" },
        "8": { "strongs": "5535", "eng": "Be silent" },
        "9": { "strongs": "8085", "eng": "and listen" },
        "10": { "strongs": "3478", "eng": "Israel" },
        "11": { "strongs": "3117", "eng": "day" },
        "12": { "strongs": "2088", "eng": "this" },
        "13": { "strongs": "1961", "eng": "you have become" },
        "14": { "strongs": "5971", "eng": "the people" },
        "15": { "strongs": "3068", "eng": "of Yahweh" },
        "16": { "strongs": "430", "eng": "your God"
        }
    },
    "10": {
        "0": { "strongs": "8085", "eng": "Therefore you shall obey" },
        "1": { "strongs": "6963", "eng": "the voice" },
        "2": { "strongs": "3069", "eng": "of Yahweh" },
        "3": { "strongs": "430", "eng": "your God" },
        "4": { "strongs": "6213", "eng": "and observe" },
        "5": { "strongs": "853", "eng": "-" },
        "6": { "strongs": "4687", "eng": "His commandments" },
        "7": { "strongs": "853", "eng": "and" },
        "8": { "strongs": "2706", "eng": "His statutes" },
        "9": { "strongs": "834", "eng": "which" },
        "10": { "strongs": "595", "eng": "I" },
        "11": { "strongs": "6680", "eng": "command you" },
        "12": { "strongs": "3117", "eng": "today"
        }
    },
    "11": {
        "0": { "strongs": "6680", "eng": "And commanded" },
        "1": { "strongs": "4872", "eng": "Moses" },
        "2": { "strongs": "853", "eng": "-" },
        "3": { "strongs": "5971", "eng": "the people" },
        "4": { "strongs": "3117", "eng": "on day" },
        "5": { "strongs": "1931", "eng": "that" },
        "6": { "strongs": "559", "eng": "saying"
        }
    },
    "12": {
        "0": { "strongs": "428", "eng": "these" },
        "1": { "strongs": "5975", "eng": "shall stand" },
        "2": { "strongs": "1288", "eng": "to bless" },
        "3": { "strongs": "853", "eng": "-" },
        "4": { "strongs": "5971", "eng": "the people" },
        "5": { "strongs": "5921", "eng": "on" },
        "6": { "strongs": "2022", "eng": "Mount" },
        "7": { "strongs": "1630", "eng": "Gerizim" },
        "8": { "strongs": "5674", "eng": "when you have crossed over" },
        "9": { "strongs": "853", "eng": "-" },
        "10": { "strongs": "3383", "eng": "the Jordan" },
        "11": { "strongs": "8095", "eng": "Simeon" },
        "12": { "strongs": "3878", "eng": "and Levi" },
        "13": { "strongs": "3063", "eng": "Judah" },
        "14": { "strongs": "3485", "eng": "and Issachar" },
        "15": { "strongs": "3130", "eng": "and Joseph" },
        "16": { "strongs": "1144", "eng": "and Benjamin"
        }
    },
    "13": {
        "0": { "strongs": "428", "eng": "And these" },
        "1": { "strongs": "5975", "eng": "shall stand" },
        "2": { "strongs": "5921", "eng": "to" },
        "3": { "strongs": "7045", "eng": "curse" },
        "4": { "strongs": "2022", "eng": "on Mount" },
        "5": { "strongs": "5858", "eng": "Ebal" },
        "6": { "strongs": "7205", "eng": "Reuben" },
        "7": { "strongs": "1410", "eng": "Gad" },
        "8": { "strongs": "836", "eng": "and Asher" },
        "9": { "strongs": "2074", "eng": "and Zebulun" },
        "10": { "strongs": "1835", "eng": "Dan" },
        "11": { "strongs": "5321", "eng": "and Naphtali"
        }
    },
    "14": {
        "0": { "strongs": "6030", "eng": "And shall speak" },
        "1": { "strongs": "3881", "eng": "the Levites" },
        "2": { "strongs": "559", "eng": "and say" },
        "3": { "strongs": "413", "eng": "to" },
        "4": { "strongs": "3605", "eng": "all" },
        "5": { "strongs": "376", "eng": "the men" },
        "6": { "strongs": "3478", "eng": "of Israel" },
        "7": { "strongs": "6963", "eng": "with a voice" },
        "8": { "strongs": "7311", "eng": "loud"
        }
    },
    "15": {
        "0": { "strongs": "779", "eng": "Cursed [is]" },
        "1": { "strongs": "376", "eng": "the man" },
        "2": { "strongs": "834", "eng": "who" },
        "3": { "strongs": "6213", "eng": "makes" },
        "4": { "strongs": "6459", "eng": "a carved" },
        "5": { "strongs": "4541", "eng": "or molded image" },
        "6": { "strongs": "8441", "eng": "an abomination to" },
        "7": { "strongs": "3068", "eng": "Yahweh" },
        "8": { "strongs": "4639", "eng": "the work" },
        "9": { "strongs": "3027", "eng": "of the hands" },
        "10": { "strongs": "2796", "eng": "of the craftsman" },
        "11": { "strongs": "7760", "eng": "and sets [it] up" },
        "12": { "strongs": "5643", "eng": "in secret" },
        "13": { "strongs": "6030", "eng": "and shall answer" },
        "14": { "strongs": "3605", "eng": "all" },
        "15": { "strongs": "5971", "eng": "the people" },
        "16": { "strongs": "559", "eng": "and say" },
        "17": { "strongs": "543", "eng": "Amen"
        }
    },
    "16": {
        "0": { "strongs": "779", "eng": "Cursed [is]" },
        "1": { "strongs": "7034", "eng": "he who dishonors" },
        "2": { "strongs": "1", "eng": "his father" },
        "3": { "strongs": "517", "eng": "or his mother" },
        "4": { "strongs": "559", "eng": "And shall say" },
        "5": { "strongs": "3605", "eng": "all" },
        "6": { "strongs": "5971", "eng": "the people" },
        "7": { "strongs": "543", "eng": "Amen"
        }
    },
    "17": {
        "0": { "strongs": "779", "eng": "Cursed [is]" },
        "1": { "strongs": "5253", "eng": "he who moves" },
        "2": { "strongs": "1366", "eng": "landmark" },
        "3": { "strongs": "7453", "eng": "Of his neighbor" },
        "4": { "strongs": "559", "eng": "and shall say" },
        "5": { "strongs": "3605", "eng": "all" },
        "6": { "strongs": "5971", "eng": "the people" },
        "7": { "strongs": "543", "eng": "Amen"
        }
    },
    "18": {
        "0": { "strongs": "779", "eng": "Cursed [is]" },
        "1": { "strongs": "7686", "eng": "wander" },
        "2": { "strongs": "5787", "eng": "he who lets a blind man" },
        "3": { "strongs": "1870", "eng": "in the road" },
        "4": { "strongs": "559", "eng": "And shall say" },
        "5": { "strongs": "3605", "eng": "all" },
        "6": { "strongs": "5971", "eng": "the people" },
        "7": { "strongs": "543", "eng": "Amen"
        }
    },
    "19": {
        "0": { "strongs": "779", "eng": "Cursed is" },
        "1": { "strongs": "5186", "eng": "he who withholds" },
        "2": { "strongs": "4941", "eng": "justice" },
        "3": { "strongs": "1616", "eng": "from the foreigner" },
        "4": { "strongs": "3490", "eng": "the fatherless" },
        "5": { "strongs": "490", "eng": "or the widow" },
        "6": { "strongs": "559", "eng": "And shall say" },
        "7": { "strongs": "3605", "eng": "all" },
        "8": { "strongs": "5971", "eng": "the people" },
        "9": { "strongs": "543", "eng": "Amen"
        }
    },
    "20": {
        "0": { "strongs": "779", "eng": "Cursed [is]" },
        "1": { "strongs": "7901", "eng": "he who lies" },
        "2": { "strongs": "5973", "eng": "with" },
        "3": { "strongs": "802", "eng": "wife" },
        "4": { "strongs": "1", "eng": "of his father" },
        "5": { "strongs": "3588", "eng": "because" },
        "6": { "strongs": "1540", "eng": "he has uncovered" },
        "7": { "strongs": "3671", "eng": "bed" },
        "8": { "strongs": "1", "eng": "Of his father" },
        "9": { "strongs": "559", "eng": "and shall say" },
        "10": { "strongs": "3605", "eng": "all" },
        "11": { "strongs": "5971", "eng": "the people" },
        "12": { "strongs": "543", "eng": "Amen"
        }
    },
    "21": {
        "0": { "strongs": "779", "eng": "Cursed [is]" },
        "1": { "strongs": "7901", "eng": "he who lies" },
        "2": { "strongs": "5973", "eng": "with" },
        "3": { "strongs": "3605", "eng": "any kind" },
        "4": { "strongs": "929", "eng": "of animal" },
        "5": { "strongs": "559", "eng": "And shall say" },
        "6": { "strongs": "3605", "eng": "all" },
        "7": { "strongs": "5971", "eng": "the people" },
        "8": { "strongs": "543", "eng": "Amen"
        }
    },
    "22": {
        "0": { "strongs": "779", "eng": "Cursed [is]" },
        "1": { "strongs": "7901", "eng": "he who lies" },
        "2": { "strongs": "5973", "eng": "with" },
        "3": { "strongs": "269", "eng": "his sister" },
        "4": { "strongs": "1323", "eng": "the daughter" },
        "5": { "strongs": "1", "eng": "of his father" },
        "6": { "strongs": "176", "eng": "or" },
        "7": { "strongs": "1323", "eng": "the daughter" },
        "8": { "strongs": "517", "eng": "of his mother" },
        "9": { "strongs": "559", "eng": "And shall say" },
        "10": { "strongs": "3605", "eng": "all" },
        "11": { "strongs": "5971", "eng": "the people" },
        "12": { "strongs": "543", "eng": "Amen"
        }
    },
    "23": {
        "0": { "strongs": "779", "eng": "Cursed [is]" },
        "1": { "strongs": "7901", "eng": "he who lies" },
        "2": { "strongs": "5973", "eng": "with" },
        "3": { "strongs": "2859", "eng": "his mother-in-law" },
        "4": { "strongs": "559", "eng": "And shall say" },
        "5": { "strongs": "3605", "eng": "all" },
        "6": { "strongs": "5971", "eng": "the people" },
        "7": { "strongs": "543", "eng": "Amen"
        }
    },
    "24": {
        "0": { "strongs": "779", "eng": "Cursed [is]" },
        "1": { "strongs": "5221", "eng": "he who strikes down" },
        "2": { "strongs": "7453", "eng": "his neighbor" },
        "3": { "strongs": "5643", "eng": "in secret" },
        "4": { "strongs": "559", "eng": "And shall say" },
        "5": { "strongs": "3605", "eng": "all" },
        "6": { "strongs": "5971", "eng": "the people" },
        "7": { "strongs": "543", "eng": "Amen"
        }
    },
    "25": {
        "0": { "strongs": "779", "eng": "Cursed [is]" },
        "1": { "strongs": "3947", "eng": "he who takes" },
        "2": { "strongs": "7810", "eng": "a bribe" },
        "3": { "strongs": "5221", "eng": "to slay" },
        "4": { "strongs": "5315", "eng": "a person" },
        "5": { "strongs": "1818", "eng": "A bloodshed" },
        "6": { "strongs": "5355", "eng": "innocent" },
        "7": { "strongs": "559", "eng": "and shall say" },
        "8": { "strongs": "3605", "eng": "all" },
        "9": { "strongs": "5971", "eng": "the people" },
        "10": { "strongs": "543", "eng": "Amen"
        }
    },
    "26": {
        "0": { "strongs": "779", "eng": "Cursed [is]" },
        "1": { "strongs": "834", "eng": "he who" },
        "2": { "strongs": "3808", "eng": "not" },
        "3": { "strongs": "6965", "eng": "does confirm" },
        "4": { "strongs": "853", "eng": "-" },
        "5": { "strongs": "1697", "eng": "[all] the words" },
        "6": { "strongs": "8451", "eng": "of law" },
        "7": { "strongs": "2063", "eng": "this" },
        "8": { "strongs": "6213", "eng": "by doing" },
        "9": { "strongs": "853", "eng": "-" },
        "10": { "strongs": "559", "eng": "and shall say" },
        "11": { "strongs": "3605", "eng": "all" },
        "12": { "strongs": "5971", "eng": "the people" },
        "13": { "strongs": "543", "eng": "Amen"
        }
    }
}