{
    "1": {
        "0": { "strongs": "559", "eng": "Said" },
        "1": { "strongs": "589", "eng": "I" },
        "2": { "strongs": "3820", "eng": "in my heart" },
        "3": { "strongs": "1980", "eng": "come" },
        "4": { "strongs": "4994", "eng": "now" },
        "5": { "strongs": "5254", "eng": "I will test you" },
        "6": { "strongs": "8057", "eng": "with mirth" },
        "7": { "strongs": "7200", "eng": "therefore enjoy" },
        "8": { "strongs": "2896", "eng": "pleasure" },
        "9": { "strongs": "2009", "eng": "but surely" },
        "10": { "strongs": "1571", "eng": "also" },
        "11": { "strongs": "1931", "eng": "that" },
        "12": { "strongs": "1892", "eng": "[was] vanity"
        }
    },
    "2": {
        "0": { "strongs": "7814", "eng": "Of laughter" },
        "1": { "strongs": "559", "eng": "I said" },
        "2": { "strongs": "1984", "eng": "Madness" },
        "3": { "strongs": "8057", "eng": "and of mirth" },
        "4": { "strongs": "4100", "eng": "what" },
        "5": { "strongs": "2090", "eng": "this" },
        "6": { "strongs": "6213", "eng": "does accomplish"
        }
    },
    "3": {
        "0": { "strongs": "8446", "eng": "I searched" },
        "1": { "strongs": "3820", "eng": "in my heart" },
        "2": { "strongs": "4900", "eng": "[how] to gratify" },
        "3": { "strongs": "3196", "eng": "with wine" },
        "4": { "strongs": "853", "eng": "-" },
        "5": { "strongs": "1320", "eng": "my flesh" },
        "6": { "strongs": "3820", "eng": "and while my heart" },
        "7": { "strongs": "5090", "eng": "guiding" },
        "8": { "strongs": "2451", "eng": "with wisdom" },
        "9": { "strongs": "270", "eng": "and how to lay hold" },
        "10": { "strongs": "5531", "eng": "on folly" },
        "11": { "strongs": "5704", "eng": "until" },
        "12": { "strongs": "834", "eng": "till" },
        "13": { "strongs": "7200", "eng": "I might see" },
        "14": { "strongs": "335", "eng": "where" },
        "15": { "strongs": "2088", "eng": "that [was]" },
        "16": { "strongs": "2896", "eng": "[was] good" },
        "17": { "strongs": "1121", "eng": "for the sons" },
        "18": { "strongs": "120", "eng": "of men" },
        "19": { "strongs": "834", "eng": "that" },
        "20": { "strongs": "6213", "eng": "to do" },
        "21": { "strongs": "8478", "eng": "under" },
        "22": { "strongs": "8064", "eng": "the heaven" },
        "23": { "strongs": "4557", "eng": "all" },
        "24": { "strongs": "3117", "eng": "days" },
        "25": { "strongs": "2416", "eng": "of their lives"
        }
    },
    "4": {
        "0": { "strongs": "1431", "eng": "I made great" },
        "1": { "strongs": "4639", "eng": "my works" },
        "2": { "strongs": "1129", "eng": "I built" },
        "3": { "strongs": "1004", "eng": "houses" },
        "4": { "strongs": "5193", "eng": "and planted" },
        "5": { "strongs": "3754", "eng": "vineyards"
        }
    },
    "5": {
        "0": { "strongs": "6213", "eng": "I made" },
        "1": { "strongs": "1593", "eng": "gardens" },
        "2": { "strongs": "6508", "eng": "and orchards" },
        "3": { "strongs": "5193", "eng": "and I planted" },
        "4": { "strongs": "6086", "eng": "trees" },
        "5": { "strongs": "3605", "eng": "all [kinds]" },
        "6": { "strongs": "6529", "eng": "of fruit"
        }
    },
    "6": {
        "0": { "strongs": "6213", "eng": "I made" },
        "1": { "strongs": "1295", "eng": "pools" },
        "2": { "strongs": "4325", "eng": "water" },
        "3": { "strongs": "8248", "eng": "to water" },
        "4": { "strongs": "1992", "eng": "from which" },
        "5": { "strongs": "3293", "eng": "the grove" },
        "6": { "strongs": "6779", "eng": "growing" },
        "7": { "strongs": "6086", "eng": "the trees of"
        }
    },
    "7": {
        "0": { "strongs": "7069", "eng": "I acquired" },
        "1": { "strongs": "5650", "eng": "male" },
        "2": { "strongs": "8198", "eng": "and maidservants" },
        "3": { "strongs": "1121", "eng": "and servants in" },
        "4": { "strongs": "1004", "eng": "house" },
        "5": { "strongs": "1961", "eng": "had born" },
        "6": { "strongs": "1571", "eng": "Yes" },
        "7": { "strongs": "4735", "eng": "possessions" },
        "8": { "strongs": "1241", "eng": "of herds" },
        "9": { "strongs": "6629", "eng": "and flocks" },
        "10": { "strongs": "7235", "eng": "greater" },
        "11": { "strongs": "1961", "eng": "I" },
        "12": { "strongs": "3605", "eng": "than all" },
        "13": { "strongs": "1961", "eng": "who were" },
        "14": { "strongs": "6440", "eng": "before me" },
        "15": { "strongs": "3389", "eng": "in Jerusalem"
        }
    },
    "8": {
        "0": { "strongs": "3664", "eng": "I gathered" },
        "1": { "strongs": "1571", "eng": "also" },
        "2": { "strongs": "3701", "eng": "silver" },
        "3": { "strongs": "2091", "eng": "and gold" },
        "4": { "strongs": "5459", "eng": "and the special treasures" },
        "5": { "strongs": "4428", "eng": "of kings" },
        "6": { "strongs": "4082", "eng": "and of the provinces" },
        "7": { "strongs": "6213", "eng": "Acquired" },
        "8": { "strongs": "7891", "eng": "male" },
        "9": { "strongs": "7891", "eng": "and female singers" },
        "10": { "strongs": "8588", "eng": "and the delights" },
        "11": { "strongs": "1121", "eng": "of the sons" },
        "12": { "strongs": "120", "eng": "of men" },
        "13": { "strongs": "7705", "eng": "many" },
        "14": { "strongs": "7705", "eng": "and [and] musical instruments of [all kinds]"
        }
    },
    "9": {
        "0": { "strongs": "1431", "eng": "so I became great" },
        "1": { "strongs": "3254", "eng": "and excelled more" },
        "2": { "strongs": "3605", "eng": "than all" },
        "3": { "strongs": "1961", "eng": "who were" },
        "4": { "strongs": "6440", "eng": "before me" },
        "5": { "strongs": "3389", "eng": "in Jerusalem" },
        "6": { "strongs": "637", "eng": "Also" },
        "7": { "strongs": "2451", "eng": "my wisdom" },
        "8": { "strongs": "5975", "eng": "remained"
        }
    },
    "10": {
        "0": { "strongs": "3605", "eng": "And" },
        "1": { "strongs": "834", "eng": "whatever" },
        "2": { "strongs": "7592", "eng": "desired" },
        "3": { "strongs": "5869", "eng": "my eyes" },
        "4": { "strongs": "3808", "eng": "not" },
        "5": { "strongs": "680", "eng": "I did keep" },
        "6": { "strongs": "1992", "eng": "from them" },
        "7": { "strongs": "3808", "eng": "not" },
        "8": { "strongs": "4513", "eng": "I did withhold" },
        "9": { "strongs": "853", "eng": "-" },
        "10": { "strongs": "3820", "eng": "my heart" },
        "11": { "strongs": "3605", "eng": "from any" },
        "12": { "strongs": "8057", "eng": "pleasure" },
        "13": { "strongs": "3588", "eng": "for" },
        "14": { "strongs": "3820", "eng": "my heart" },
        "15": { "strongs": "8055", "eng": "rejoiced" },
        "16": { "strongs": "3605", "eng": "in all" },
        "17": { "strongs": "5999", "eng": "my labor" },
        "18": { "strongs": "2088", "eng": "and this" },
        "19": { "strongs": "1961", "eng": "was" },
        "20": { "strongs": "2506", "eng": "my reward" },
        "21": { "strongs": "3605", "eng": "from all" },
        "22": { "strongs": "5999", "eng": "my labor"
        }
    },
    "11": {
        "0": { "strongs": "6437", "eng": "And looked" },
        "1": { "strongs": "589", "eng": "I" },
        "2": { "strongs": "3605", "eng": "on all" },
        "3": { "strongs": "4639", "eng": "the works" },
        "4": { "strongs": "6213", "eng": "that had done" },
        "5": { "strongs": "3027", "eng": "my hands" },
        "6": { "strongs": "5999", "eng": "and on the labor" },
        "7": { "strongs": "5998", "eng": "in which I had toiled" },
        "8": { "strongs": "6213", "eng": "to do" },
        "9": { "strongs": "2009", "eng": "and indeed" },
        "10": { "strongs": "3605", "eng": "all" },
        "11": { "strongs": "1892", "eng": "[was] vanity" },
        "12": { "strongs": "7469", "eng": "and grasping for" },
        "13": { "strongs": "7307", "eng": "the wind" },
        "14": { "strongs": "369", "eng": "and [There was] no" },
        "15": { "strongs": "3504", "eng": "profit" },
        "16": { "strongs": "8478", "eng": "under" },
        "17": { "strongs": "8121", "eng": "the sun"
        }
    },
    "12": {
        "0": { "strongs": "6437", "eng": "And turned" },
        "1": { "strongs": "589", "eng": "I" },
        "2": { "strongs": "7200", "eng": "to consider" },
        "3": { "strongs": "2451", "eng": "wisdom" },
        "4": { "strongs": "1947", "eng": "and madness" },
        "5": { "strongs": "5531", "eng": "and folly" },
        "6": { "strongs": "3588", "eng": "for" },
        "7": { "strongs": "4100", "eng": "what [can do]" },
        "8": { "strongs": "120", "eng": "the man" },
        "9": { "strongs": "935", "eng": "who succeeds" },
        "10": { "strongs": "310", "eng": "after" },
        "11": { "strongs": "4428", "eng": "the king" },
        "12": { "strongs": "853", "eng": "-" },
        "13": { "strongs": "834", "eng": "[Only] what" },
        "14": { "strongs": "3528", "eng": "already" },
        "15": { "strongs": "6213", "eng": "he has done"
        }
    },
    "13": {
        "0": { "strongs": "7200", "eng": "And saw" },
        "1": { "strongs": "589", "eng": "I" },
        "2": { "strongs": "3426", "eng": "that" },
        "3": { "strongs": "3504", "eng": "excels" },
        "4": { "strongs": "2451", "eng": "wisdom" },
        "5": { "strongs": "4480", "eng": "from" },
        "6": { "strongs": "5531", "eng": "folly" },
        "7": { "strongs": "3504", "eng": "as excels" },
        "8": { "strongs": "216", "eng": "light" },
        "9": { "strongs": "4480", "eng": "from" },
        "10": { "strongs": "2822", "eng": "darkness"
        }
    },
    "14": {
        "0": { "strongs": "2450", "eng": "Of the wise man" },
        "1": { "strongs": "5869", "eng": "eyes [are]" },
        "2": { "strongs": "7218", "eng": "in his head" },
        "3": { "strongs": "3684", "eng": "but the fool" },
        "4": { "strongs": "2822", "eng": "in darkness" },
        "5": { "strongs": "1980", "eng": "Walks" },
        "6": { "strongs": "3045", "eng": "and yet perceived" },
        "7": { "strongs": "1571", "eng": "also" },
        "8": { "strongs": "589", "eng": "I" },
        "9": { "strongs": "4745", "eng": "that the event" },
        "10": { "strongs": "259", "eng": "one" },
        "11": { "strongs": "7136", "eng": "happens to" },
        "12": { "strongs": "853", "eng": "-" },
        "13": { "strongs": "3605", "eng": "them all"
        }
    },
    "15": {
        "0": { "strongs": "559", "eng": "So said" },
        "1": { "strongs": "589", "eng": "I" },
        "2": { "strongs": "3820", "eng": "in my heart" },
        "3": { "strongs": "4745", "eng": "as it happens to" },
        "4": { "strongs": "3684", "eng": "the fool" },
        "5": { "strongs": "1571", "eng": "also" },
        "6": { "strongs": "589", "eng": "me" },
        "7": { "strongs": "7136", "eng": "it happens to" },
        "8": { "strongs": "4100", "eng": "and why" },
        "9": { "strongs": "2449", "eng": "was wise" },
        "10": { "strongs": "589", "eng": "I" },
        "11": { "strongs": "227", "eng": "then" },
        "12": { "strongs": "3148", "eng": "more" },
        "13": { "strongs": "1696", "eng": "and I said" },
        "14": { "strongs": "3820", "eng": "in my heart" },
        "15": { "strongs": "1571", "eng": "also" },
        "16": { "strongs": "2088", "eng": "this" },
        "17": { "strongs": "1892", "eng": "[is] vanity"
        }
    },
    "16": {
        "0": { "strongs": "3588", "eng": "For" },
        "1": { "strongs": "369", "eng": "[there is] no" },
        "2": { "strongs": "2146", "eng": "remembrance" },
        "3": { "strongs": "2450", "eng": "of the wise" },
        "4": { "strongs": "5973", "eng": "more than" },
        "5": { "strongs": "3684", "eng": "of the fool" },
        "6": { "strongs": "5769", "eng": "forever" },
        "7": { "strongs": "3528", "eng": "Since that now [is]" },
        "8": { "strongs": "3117", "eng": "in the days" },
        "9": { "strongs": "935", "eng": "to come" },
        "10": { "strongs": "3605", "eng": "all" },
        "11": { "strongs": "7911", "eng": "will be forgotten" },
        "12": { "strongs": "349", "eng": "And how" },
        "13": { "strongs": "4191", "eng": "does die" },
        "14": { "strongs": "2450", "eng": "a wise [man]" },
        "15": { "strongs": "5973", "eng": "as" },
        "16": { "strongs": "3684", "eng": "the fool"
        }
    },
    "17": {
        "0": { "strongs": "8130", "eng": "Therefore I hated" },
        "1": { "strongs": "853", "eng": "-" },
        "2": { "strongs": "2416", "eng": "life" },
        "3": { "strongs": "3588", "eng": "because" },
        "4": { "strongs": "7451", "eng": "[was] distressing" },
        "5": { "strongs": "5921", "eng": "to me" },
        "6": { "strongs": "4639", "eng": "the work" },
        "7": { "strongs": "6213", "eng": "that was done" },
        "8": { "strongs": "8478", "eng": "under" },
        "9": { "strongs": "8121", "eng": "the sun" },
        "10": { "strongs": "3588", "eng": "for" },
        "11": { "strongs": "3605", "eng": "all" },
        "12": { "strongs": "1892", "eng": "[is] vanity" },
        "13": { "strongs": "7469", "eng": "and grasping for" },
        "14": { "strongs": "7307", "eng": "the wind"
        }
    },
    "18": {
        "0": { "strongs": "8130", "eng": "And hated" },
        "1": { "strongs": "589", "eng": "I" },
        "2": { "strongs": "853", "eng": "-" },
        "3": { "strongs": "3605", "eng": "all" },
        "4": { "strongs": "5999", "eng": "my labor" },
        "5": { "strongs": "589", "eng": "in which I" },
        "6": { "strongs": "6001", "eng": "had toiled" },
        "7": { "strongs": "8478", "eng": "under" },
        "8": { "strongs": "8121", "eng": "the sun" },
        "9": { "strongs": "3240", "eng": "because I must leave it" },
        "10": { "strongs": "120", "eng": "to the man" },
        "11": { "strongs": "1961", "eng": "who will come" },
        "12": { "strongs": "310", "eng": "after me"
        }
    },
    "19": {
        "0": { "strongs": "4310", "eng": "And who" },
        "1": { "strongs": "3045", "eng": "knows" },
        "2": { "strongs": "2450", "eng": "whether wise" },
        "3": { "strongs": "1961", "eng": "he will be" },
        "4": { "strongs": "176", "eng": "or" },
        "5": { "strongs": "5530", "eng": "a fool" },
        "6": { "strongs": "7980", "eng": "and yet he will rule" },
        "7": { "strongs": "3605", "eng": "over all" },
        "8": { "strongs": "5999", "eng": "my labor" },
        "9": { "strongs": "5998", "eng": "in which toiled I" },
        "10": { "strongs": "2449", "eng": "and in which I have shown myself wise" },
        "11": { "strongs": "8478", "eng": "under" },
        "12": { "strongs": "8121", "eng": "the sun" },
        "13": { "strongs": "1571", "eng": "Also" },
        "14": { "strongs": "2088", "eng": "this" },
        "15": { "strongs": "1892", "eng": "[is] vanity"
        }
    },
    "20": {
        "0": { "strongs": "5437", "eng": "Therefore turned" },
        "1": { "strongs": "589", "eng": "I" },
        "2": { "strongs": "2976", "eng": "and despaired" },
        "3": { "strongs": "853", "eng": "-" },
        "4": { "strongs": "3820", "eng": "my heart" },
        "5": { "strongs": "5921", "eng": "of" },
        "6": { "strongs": "3605", "eng": "all" },
        "7": { "strongs": "5999", "eng": "the labor" },
        "8": { "strongs": "5998", "eng": "in which I had toiled" },
        "9": { "strongs": "8478", "eng": "under" },
        "10": { "strongs": "8121", "eng": "the sun"
        }
    },
    "21": {
        "0": { "strongs": "3588", "eng": "For" },
        "1": { "strongs": "3426", "eng": "there is" },
        "2": { "strongs": "120", "eng": "a man" },
        "3": { "strongs": "5999", "eng": "whose labor [is]" },
        "4": { "strongs": "2451", "eng": "with wisdom" },
        "5": { "strongs": "1847", "eng": "and knowledge" },
        "6": { "strongs": "3788", "eng": "and skill" },
        "7": { "strongs": "120", "eng": "and yet to a man" },
        "8": { "strongs": "3808", "eng": "who not" },
        "9": { "strongs": "5998", "eng": "has labored" },
        "10": { "strongs": "5414", "eng": "he must leave" },
        "11": { "strongs": "2506", "eng": "his heritage" },
        "12": { "strongs": "1571", "eng": "Also" },
        "13": { "strongs": "2088", "eng": "this" },
        "14": { "strongs": "1892", "eng": "[is] vanity" },
        "15": { "strongs": "7451", "eng": "and a evil" },
        "16": { "strongs": "7227", "eng": "great"
        }
    },
    "22": {
        "0": { "strongs": "3588", "eng": "For" },
        "1": { "strongs": "4100", "eng": "what" },
        "2": { "strongs": "1933", "eng": "has" },
        "3": { "strongs": "120", "eng": "man" },
        "4": { "strongs": "3605", "eng": "for all" },
        "5": { "strongs": "5999", "eng": "his labor" },
        "6": { "strongs": "7475", "eng": "for the striving" },
        "7": { "strongs": "3820", "eng": "of his heart" },
        "8": { "strongs": "1931", "eng": "with which he" },
        "9": { "strongs": "6001", "eng": "has toiled" },
        "10": { "strongs": "8478", "eng": "under" },
        "11": { "strongs": "8121", "eng": "the sun"
        }
    },
    "23": {
        "0": { "strongs": "3588", "eng": "for" },
        "1": { "strongs": "3605", "eng": "all" },
        "2": { "strongs": "3117", "eng": "his days" },
        "3": { "strongs": "4341", "eng": "[are] sorrowful" },
        "4": { "strongs": "3708", "eng": "and burdensome" },
        "5": { "strongs": "6045", "eng": "his work" },
        "6": { "strongs": "1571", "eng": "even" },
        "7": { "strongs": "3915", "eng": "in the night" },
        "8": { "strongs": "3808", "eng": "No" },
        "9": { "strongs": "7901", "eng": "takes rest" },
        "10": { "strongs": "3820", "eng": "his heart" },
        "11": { "strongs": "1571", "eng": "also" },
        "12": { "strongs": "2088", "eng": "this" },
        "13": { "strongs": "1892", "eng": "vanity" },
        "14": { "strongs": "1931", "eng": "is"
        }
    },
    "24": {
        "0": { "strongs": "369", "eng": "Nothing [is]" },
        "1": { "strongs": "2896", "eng": "better" },
        "2": { "strongs": "120", "eng": "for a man" },
        "3": { "strongs": "398", "eng": "[than] that he should eat" },
        "4": { "strongs": "8354", "eng": "and drink" },
        "5": { "strongs": "3318", "eng": "and [that] should enjoy" },
        "6": { "strongs": "853", "eng": "-" },
        "7": { "strongs": "5315", "eng": "his soul" },
        "8": { "strongs": "2896", "eng": "good" },
        "9": { "strongs": "5999", "eng": "in his labor" },
        "10": { "strongs": "1571", "eng": "Also" },
        "11": { "strongs": "2090", "eng": "this" },
        "12": { "strongs": "7200", "eng": "saw" },
        "13": { "strongs": "589", "eng": "I" },
        "14": { "strongs": "3588", "eng": "that [was]" },
        "15": { "strongs": "3027", "eng": "from the hand" },
        "16": { "strongs": "430", "eng": "of God" },
        "17": { "strongs": "1931", "eng": "was"
        }
    },
    "25": {
        "0": { "strongs": "3588", "eng": "For" },
        "1": { "strongs": "4310", "eng": "who" },
        "2": { "strongs": "398", "eng": "can eat" },
        "3": { "strongs": "4310", "eng": "or who" },
        "4": { "strongs": "2363", "eng": "can have enjoyment" },
        "5": { "strongs": "2351", "eng": "more" },
        "6": { "strongs": "4480", "eng": "than I"
        }
    },
    "26": {
        "0": { "strongs": "3588", "eng": "For" },
        "1": { "strongs": "120", "eng": "to a man" },
        "2": { "strongs": "2896", "eng": "who [is] good" },
        "3": { "strongs": "6440", "eng": "in His sight" },
        "4": { "strongs": "5414", "eng": "[God] gives" },
        "5": { "strongs": "2451", "eng": "wisdom" },
        "6": { "strongs": "1847", "eng": "and knowledge" },
        "7": { "strongs": "8057", "eng": "and joy" },
        "8": { "strongs": "2398", "eng": "but to the sinner" },
        "9": { "strongs": "5414", "eng": "he gives" },
        "10": { "strongs": "6045", "eng": "the work" },
        "11": { "strongs": "622", "eng": "of gathering" },
        "12": { "strongs": "3664", "eng": "and collecting" },
        "13": { "strongs": "5414", "eng": "that He may give" },
        "14": { "strongs": "2896", "eng": "to [him who is] good" },
        "15": { "strongs": "6440", "eng": "before" },
        "16": { "strongs": "430", "eng": "God" },
        "17": { "strongs": "1571", "eng": "Also" },
        "18": { "strongs": "2088", "eng": "this" },
        "19": { "strongs": "1892", "eng": "[is] vanity" },
        "20": { "strongs": "7469", "eng": "and grasping for" },
        "21": { "strongs": "7307", "eng": "the wind"
        }
    }
}